{
  "expand": "renderedFields,names,schema,operations,editmeta,changelog,versionedRepresentations",
  "id": "419653",
  "self": "https://suporte.maximatech.com.br/rest/api/2/issue/419653",
  "key": "GATE-47",
  "fields": {
    "summary": "Preço Fixo não valida para Filial 07",
    "created": "2024-09-11T08:58:56.488-0300",
    "description": "- O preço fixo para o produto 8153 destinado a filial 07 e 50, não está sendo apresentado no APP;\r\n\r\n- Foi feita a atualização do ambiente nuvem e local do cliente, no qual estava divergênte e nesse processo o preço fixo para filial 50 tornou a validar, porém para filial 07, mesmo com registro na base do RCA, não é apresentado;",
    "reporter": {
      "self": "https://suporte.maximatech.com.br/rest/api/2/user?username=pedro.moura",
      "name": "pedro.moura",
      "key": "pedro.moura",
      "emailAddress": "pedro.moura@maximatech.com.br",
      "avatarUrls": {
        "48x48": "https://suporte.maximatech.com.br/secure/useravatar?ownerId=pedro.moura&avatarId=16810",
        "24x24": "https://suporte.maximatech.com.br/secure/useravatar?size=small&ownerId=pedro.moura&avatarId=16810",
        "16x16": "https://suporte.maximatech.com.br/secure/useravatar?size=xsmall&ownerId=pedro.moura&avatarId=16810",
        "32x32": "https://suporte.maximatech.com.br/secure/useravatar?size=medium&ownerId=pedro.moura&avatarId=16810"
      },
      "displayName": "Pedro Henrique Rodrigues Moura",
      "active": true,
      "timeZone": "America/Argentina/Buenos_Aires"
    },
    "customfield_10320": {
      "self": "https://suporte.maximatech.com.br/rest/api/2/customFieldOption/15831",
      "value": "MXPED - Política de Desconto - Preço Fixo",
      "id": "15831"
    },
    "customfield_10221": "- Login: comercialp.lfloriano\r\n\r\n- Iniciar Pedido P/ Cliente: 4924;\r\n- Filial 07;\r\n- Produto: 8153;\r\n- +Info / Politicas Comerciais;",
    "customfield_10232": {
      "self": "https://suporte.maximatech.com.br/rest/api/2/customFieldOption/10418",
      "value": "Winthor",
      "id": "10418"
    },
    "customfield_10222": null,
    "customfield_10223": null,
    "attachment": [
      {
        "self": "https://suporte.maximatech.com.br/rest/api/2/attachment/354089",
        "id": "354089",
        "filename": "20_3.237.1_11-09-2024.zip",
        "author": {
          "self": "https://suporte.maximatech.com.br/rest/api/2/user?username=pedro.moura",
          "name": "pedro.moura",
          "key": "pedro.moura",
          "emailAddress": "pedro.moura@maximatech.com.br",
          "avatarUrls": {
            "48x48": "https://suporte.maximatech.com.br/secure/useravatar?ownerId=pedro.moura&avatarId=16810",
            "24x24": "https://suporte.maximatech.com.br/secure/useravatar?size=small&ownerId=pedro.moura&avatarId=16810",
            "16x16": "https://suporte.maximatech.com.br/secure/useravatar?size=xsmall&ownerId=pedro.moura&avatarId=16810",
            "32x32": "https://suporte.maximatech.com.br/secure/useravatar?size=medium&ownerId=pedro.moura&avatarId=16810"
          },
          "displayName": "Pedro Henrique Rodrigues Moura",
          "active": true,
          "timeZone": "America/Argentina/Buenos_Aires"
        },
        "created": "2024-09-11T08:59:28.321-0300",
        "size": 47553429,
        "mimeType": "application/zip",
        "content": "https://suporte.maximatech.com.br/secure/attachment/354089/20_3.237.1_11-09-2024.zip"
      },
      {
        "self": "https://suporte.maximatech.com.br/rest/api/2/attachment/354094",
        "id": "354094",
        "filename": "316.png",
        "author": {
          "self": "https://suporte.maximatech.com.br/rest/api/2/user?username=pedro.moura",
          "name": "pedro.moura",
          "key": "pedro.moura",
          "emailAddress": "pedro.moura@maximatech.com.br",
          "avatarUrls": {
            "48x48": "https://suporte.maximatech.com.br/secure/useravatar?ownerId=pedro.moura&avatarId=16810",
            "24x24": "https://suporte.maximatech.com.br/secure/useravatar?size=small&ownerId=pedro.moura&avatarId=16810",
            "16x16": "https://suporte.maximatech.com.br/secure/useravatar?size=xsmall&ownerId=pedro.moura&avatarId=16810",
            "32x32": "https://suporte.maximatech.com.br/secure/useravatar?size=medium&ownerId=pedro.moura&avatarId=16810"
          },
          "displayName": "Pedro Henrique Rodrigues Moura",
          "active": true,
          "timeZone": "America/Argentina/Buenos_Aires"
        },
        "created": "2024-09-11T09:09:50.014-0300",
        "size": 312193,
        "mimeType": "image/png",
        "content": "https://suporte.maximatech.com.br/secure/attachment/354094/316.png",
        "thumbnail": "https://suporte.maximatech.com.br/secure/thumbnail/354094/_thumb_354094.png"
      },
      {
        "self": "https://suporte.maximatech.com.br/rest/api/2/attachment/354184",
        "id": "354184",
        "filename": "Screenshot_1.png",
        "author": {
          "self": "https://suporte.maximatech.com.br/rest/api/2/user?username=filipe.padilha",
          "name": "filipe.padilha",
          "key": "filipe.padilha",
          "emailAddress": "filipe.padilha@maximatech.com.br",
          "avatarUrls": {
            "48x48": "https://suporte.maximatech.com.br/secure/useravatar?ownerId=filipe.padilha&avatarId=17111",
            "24x24": "https://suporte.maximatech.com.br/secure/useravatar?size=small&ownerId=filipe.padilha&avatarId=17111",
            "16x16": "https://suporte.maximatech.com.br/secure/useravatar?size=xsmall&ownerId=filipe.padilha&avatarId=17111",
            "32x32": "https://suporte.maximatech.com.br/secure/useravatar?size=medium&ownerId=filipe.padilha&avatarId=17111"
          },
          "displayName": "Filipe do Amaral Padilha",
          "active": true,
          "timeZone": "America/Argentina/Buenos_Aires"
        },
        "created": "2024-09-11T13:11:50.226-0300",
        "size": 99843,
        "mimeType": "image/png",
        "content": "https://suporte.maximatech.com.br/secure/attachment/354184/Screenshot_1.png",
        "thumbnail": "https://suporte.maximatech.com.br/secure/thumbnail/354184/_thumb_354184.png"
      },
      {
        "self": "https://suporte.maximatech.com.br/rest/api/2/attachment/354185",
        "id": "354185",
        "filename": "Screenshot_2.png",
        "author": {
          "self": "https://suporte.maximatech.com.br/rest/api/2/user?username=filipe.padilha",
          "name": "filipe.padilha",
          "key": "filipe.padilha",
          "emailAddress": "filipe.padilha@maximatech.com.br",
          "avatarUrls": {
            "48x48": "https://suporte.maximatech.com.br/secure/useravatar?ownerId=filipe.padilha&avatarId=17111",
            "24x24": "https://suporte.maximatech.com.br/secure/useravatar?size=small&ownerId=filipe.padilha&avatarId=17111",
            "16x16": "https://suporte.maximatech.com.br/secure/useravatar?size=xsmall&ownerId=filipe.padilha&avatarId=17111",
            "32x32": "https://suporte.maximatech.com.br/secure/useravatar?size=medium&ownerId=filipe.padilha&avatarId=17111"
          },
          "displayName": "Filipe do Amaral Padilha",
          "active": true,
          "timeZone": "America/Argentina/Buenos_Aires"
        },
        "created": "2024-09-11T13:11:50.199-0300",
        "size": 67362,
        "mimeType": "image/png",
        "content": "https://suporte.maximatech.com.br/secure/attachment/354185/Screenshot_2.png",
        "thumbnail": "https://suporte.maximatech.com.br/secure/thumbnail/354185/_thumb_354185.png"
      },
      {
        "self": "https://suporte.maximatech.com.br/rest/api/2/attachment/354183",
        "id": "354183",
        "filename": "Screenshot_3.png",
        "author": {
          "self": "https://suporte.maximatech.com.br/rest/api/2/user?username=filipe.padilha",
          "name": "filipe.padilha",
          "key": "filipe.padilha",
          "emailAddress": "filipe.padilha@maximatech.com.br",
          "avatarUrls": {
            "48x48": "https://suporte.maximatech.com.br/secure/useravatar?ownerId=filipe.padilha&avatarId=17111",
            "24x24": "https://suporte.maximatech.com.br/secure/useravatar?size=small&ownerId=filipe.padilha&avatarId=17111",
            "16x16": "https://suporte.maximatech.com.br/secure/useravatar?size=xsmall&ownerId=filipe.padilha&avatarId=17111",
            "32x32": "https://suporte.maximatech.com.br/secure/useravatar?size=medium&ownerId=filipe.padilha&avatarId=17111"
          },
          "displayName": "Filipe do Amaral Padilha",
          "active": true,
          "timeZone": "America/Argentina/Buenos_Aires"
        },
        "created": "2024-09-11T13:11:50.296-0300",
        "size": 84677,
        "mimeType": "image/png",
        "content": "https://suporte.maximatech.com.br/secure/attachment/354183/Screenshot_3.png",
        "thumbnail": "https://suporte.maximatech.com.br/secure/thumbnail/354183/_thumb_354183.png"
      },
      {
        "self": "https://suporte.maximatech.com.br/rest/api/2/attachment/354090",
        "id": "354090",
        "filename": "Screenshot_94.png",
        "author": {
          "self": "https://suporte.maximatech.com.br/rest/api/2/user?username=pedro.moura",
          "name": "pedro.moura",
          "key": "pedro.moura",
          "emailAddress": "pedro.moura@maximatech.com.br",
          "avatarUrls": {
            "48x48": "https://suporte.maximatech.com.br/secure/useravatar?ownerId=pedro.moura&avatarId=16810",
            "24x24": "https://suporte.maximatech.com.br/secure/useravatar?size=small&ownerId=pedro.moura&avatarId=16810",
            "16x16": "https://suporte.maximatech.com.br/secure/useravatar?size=xsmall&ownerId=pedro.moura&avatarId=16810",
            "32x32": "https://suporte.maximatech.com.br/secure/useravatar?size=medium&ownerId=pedro.moura&avatarId=16810"
          },
          "displayName": "Pedro Henrique Rodrigues Moura",
          "active": true,
          "timeZone": "America/Argentina/Buenos_Aires"
        },
        "created": "2024-09-11T09:01:30.970-0300",
        "size": 56540,
        "mimeType": "image/png",
        "content": "https://suporte.maximatech.com.br/secure/attachment/354090/Screenshot_94.png",
        "thumbnail": "https://suporte.maximatech.com.br/secure/thumbnail/354090/_thumb_354090.png"
      },
      {
        "self": "https://suporte.maximatech.com.br/rest/api/2/attachment/354091",
        "id": "354091",
        "filename": "Screenshot_95.png",
        "author": {
          "self": "https://suporte.maximatech.com.br/rest/api/2/user?username=pedro.moura",
          "name": "pedro.moura",
          "key": "pedro.moura",
          "emailAddress": "pedro.moura@maximatech.com.br",
          "avatarUrls": {
            "48x48": "https://suporte.maximatech.com.br/secure/useravatar?ownerId=pedro.moura&avatarId=16810",
            "24x24": "https://suporte.maximatech.com.br/secure/useravatar?size=small&ownerId=pedro.moura&avatarId=16810",
            "16x16": "https://suporte.maximatech.com.br/secure/useravatar?size=xsmall&ownerId=pedro.moura&avatarId=16810",
            "32x32": "https://suporte.maximatech.com.br/secure/useravatar?size=medium&ownerId=pedro.moura&avatarId=16810"
          },
          "displayName": "Pedro Henrique Rodrigues Moura",
          "active": true,
          "timeZone": "America/Argentina/Buenos_Aires"
        },
        "created": "2024-09-11T09:01:30.900-0300",
        "size": 49746,
        "mimeType": "image/png",
        "content": "https://suporte.maximatech.com.br/secure/attachment/354091/Screenshot_95.png",
        "thumbnail": "https://suporte.maximatech.com.br/secure/thumbnail/354091/_thumb_354091.png"
      },
      {
        "self": "https://suporte.maximatech.com.br/rest/api/2/attachment/354092",
        "id": "354092",
        "filename": "Screenshot_96.png",
        "author": {
          "self": "https://suporte.maximatech.com.br/rest/api/2/user?username=pedro.moura",
          "name": "pedro.moura",
          "key": "pedro.moura",
          "emailAddress": "pedro.moura@maximatech.com.br",
          "avatarUrls": {
            "48x48": "https://suporte.maximatech.com.br/secure/useravatar?ownerId=pedro.moura&avatarId=16810",
            "24x24": "https://suporte.maximatech.com.br/secure/useravatar?size=small&ownerId=pedro.moura&avatarId=16810",
            "16x16": "https://suporte.maximatech.com.br/secure/useravatar?size=xsmall&ownerId=pedro.moura&avatarId=16810",
            "32x32": "https://suporte.maximatech.com.br/secure/useravatar?size=medium&ownerId=pedro.moura&avatarId=16810"
          },
          "displayName": "Pedro Henrique Rodrigues Moura",
          "active": true,
          "timeZone": "America/Argentina/Buenos_Aires"
        },
        "created": "2024-09-11T09:01:31.237-0300",
        "size": 355600,
        "mimeType": "image/png",
        "content": "https://suporte.maximatech.com.br/secure/attachment/354092/Screenshot_96.png",
        "thumbnail": "https://suporte.maximatech.com.br/secure/thumbnail/354092/_thumb_354092.png"
      },
      {
        "self": "https://suporte.maximatech.com.br/rest/api/2/attachment/354093",
        "id": "354093",
        "filename": "Screenshot_97.png",
        "author": {
          "self": "https://suporte.maximatech.com.br/rest/api/2/user?username=pedro.moura",
          "name": "pedro.moura",
          "key": "pedro.moura",
          "emailAddress": "pedro.moura@maximatech.com.br",
          "avatarUrls": {
            "48x48": "https://suporte.maximatech.com.br/secure/useravatar?ownerId=pedro.moura&avatarId=16810",
            "24x24": "https://suporte.maximatech.com.br/secure/useravatar?size=small&ownerId=pedro.moura&avatarId=16810",
            "16x16": "https://suporte.maximatech.com.br/secure/useravatar?size=xsmall&ownerId=pedro.moura&avatarId=16810",
            "32x32": "https://suporte.maximatech.com.br/secure/useravatar?size=medium&ownerId=pedro.moura&avatarId=16810"
          },
          "displayName": "Pedro Henrique Rodrigues Moura",
          "active": true,
          "timeZone": "America/Argentina/Buenos_Aires"
        },
        "created": "2024-09-11T09:01:30.915-0300",
        "size": 17043,
        "mimeType": "image/png",
        "content": "https://suporte.maximatech.com.br/secure/attachment/354093/Screenshot_97.png",
        "thumbnail": "https://suporte.maximatech.com.br/secure/thumbnail/354093/_thumb_354093.png"
      }
    ],
    "customfield_10407": {
      "self": "https://suporte.maximatech.com.br/rest/api/2/customFieldOption/10406",
      "value": "Dúvida",
      "id": "10406"
    },
    "comment": {
      "comments": [
        {
          "self": "https://suporte.maximatech.com.br/rest/api/2/issue/419653/comment/393985",
          "id": "393985",
          "author": {
            "self": "https://suporte.maximatech.com.br/rest/api/2/user?username=filipe.padilha",
            "name": "filipe.padilha",
            "key": "filipe.padilha",
            "emailAddress": "filipe.padilha@maximatech.com.br",
            "avatarUrls": {
              "48x48": "https://suporte.maximatech.com.br/secure/useravatar?ownerId=filipe.padilha&avatarId=17111",
              "24x24": "https://suporte.maximatech.com.br/secure/useravatar?size=small&ownerId=filipe.padilha&avatarId=17111",
              "16x16": "https://suporte.maximatech.com.br/secure/useravatar?size=xsmall&ownerId=filipe.padilha&avatarId=17111",
              "32x32": "https://suporte.maximatech.com.br/secure/useravatar?size=medium&ownerId=filipe.padilha&avatarId=17111"
            },
            "displayName": "Filipe do Amaral Padilha",
            "active": true,
            "timeZone": "America/Argentina/Buenos_Aires"
          },
          "body": "O problema ocorre porque ao trocar a filial de venda de 50 para 7, \"por baixo dos panos\", a filialNF não é alterada junto.\r\n\r\nNa prática o que ocorre é o pedido inicia na filial 50 com filialnf 50. Quando o RCA troca para filial 7, a filialnf continua na 50. Com isso, a política de preço fixo não é validada porque a filial de venda é 7, mas a filialnf sendo 50, busca dados da região 50.\r\n\r\nO responsável por mudar esse comportamento, é o parâmetro IGUALAR_FILIALNF_AO_ALTERAR_FILIAL que não está cadastrado para todos os RCAs nesse cliente. Verifique no bd nuvem:\r\nSELECT * FROM MXSPARAMETRO WHERE NOME LIKE '%IGUALAR_FILIALNF_AO_ALTERAR_FILIAL%';\r\n\r\nEntão uma das opções que eles tem para resolver essa situação é ativar esse parâmetro, colocando ele IGUALAR_FILIALNF_AO_ALTERAR_FILIAL = S.\r\n\r\nUma recomendação minha, nem precisa avisar ao cliente porque não vai ter impactos negativos. Desativar o parâmetro FILIALNF_DEFINE_FILIAL_PEDIDO.\r\n\r\nSe o cliente quiser também optar por selecionar a filialnf nos pedidos, ele pode habilitar a permissão para os RCAs: \"Permitir escolha da filial de emissão da NF\"\r\n\r\nNão vai ter impacto para esse cliente configurar o sistema dessa forma, porque ele não usa filialnf nos cadastros dos clientes dele.\r\nEu validei assim:\r\nSELECT * FROM MXSCLIENT WHERE CODFILIALNF IS NOT NULL AND CODOPERACAO <> 2;",
          "updateAuthor": {
            "self": "https://suporte.maximatech.com.br/rest/api/2/user?username=filipe.padilha",
            "name": "filipe.padilha",
            "key": "filipe.padilha",
            "emailAddress": "filipe.padilha@maximatech.com.br",
            "avatarUrls": {
              "48x48": "https://suporte.maximatech.com.br/secure/useravatar?ownerId=filipe.padilha&avatarId=17111",
              "24x24": "https://suporte.maximatech.com.br/secure/useravatar?size=small&ownerId=filipe.padilha&avatarId=17111",
              "16x16": "https://suporte.maximatech.com.br/secure/useravatar?size=xsmall&ownerId=filipe.padilha&avatarId=17111",
              "32x32": "https://suporte.maximatech.com.br/secure/useravatar?size=medium&ownerId=filipe.padilha&avatarId=17111"
            },
            "displayName": "Filipe do Amaral Padilha",
            "active": true,
            "timeZone": "America/Argentina/Buenos_Aires"
          },
          "created": "2024-09-11T13:11:37.923-0300",
          "updated": "2024-09-11T13:11:37.923-0300"
        }
      ],
      "maxResults": 1,
      "total": 1,
      "startAt": 0
    },
    "assignee": {
      "self": "https://suporte.maximatech.com.br/rest/api/2/user?username=filipe.padilha",
      "name": "filipe.padilha",
      "key": "filipe.padilha",
      "emailAddress": "filipe.padilha@maximatech.com.br",
      "avatarUrls": {
        "48x48": "https://suporte.maximatech.com.br/secure/useravatar?ownerId=filipe.padilha&avatarId=17111",
        "24x24": "https://suporte.maximatech.com.br/secure/useravatar?size=small&ownerId=filipe.padilha&avatarId=17111",
        "16x16": "https://suporte.maximatech.com.br/secure/useravatar?size=xsmall&ownerId=filipe.padilha&avatarId=17111",
        "32x32": "https://suporte.maximatech.com.br/secure/useravatar?size=medium&ownerId=filipe.padilha&avatarId=17111"
      },
      "displayName": "Filipe do Amaral Padilha",
      "active": true,
      "timeZone": "America/Argentina/Buenos_Aires"
    },
    "updated": "2024-09-11T13:11:50.982-0300",
    "status": {
      "self": "https://suporte.maximatech.com.br/rest/api/2/status/10001",
      "description": "",
      "iconUrl": "https://suporte.maximatech.com.br/images/icons/statuses/generic.png",
      "name": "RESOLVIDO",
      "id": "10001",
      "statusCategory": {
        "self": "https://suporte.maximatech.com.br/rest/api/2/statuscategory/3",
        "id": 3,
        "key": "done",
        "colorName": "green",
        "name": "Concluído"
      }
    }
  }
}
